cryptocourse/aes.py
cryptocourse/aesModeOfOperation.py
cryptocourse/argon2.py
cryptocourse/basic_bc.py
cryptocourse/basic_crypto.py
cryptocourse/basic_dh.py
cryptocourse/basic_ec.py
cryptocourse/basic_merkle_tree.py
cryptocourse/basic_mpc.py
cryptocourse/euclidean.py
cryptocourse/galois.py
cryptocourse/hkdf.py
cryptocourse/permute.py
cryptocourse/primes.py
cryptocourse/rsa_square_attack.py
cryptocourse/shamir.py
cryptocourse-1.1.0.dist-info/LICENSE
cryptocourse-1.1.0.dist-info/METADATA
cryptocourse-1.1.0.dist-info/WHEEL
cryptocourse-1.1.0.dist-info/top_level.txt
cryptocourse-1.1.0.dist-info/RECORD
