Metadata-Version: 2.1
Name: cryptocourse
Version: 1.1.0
Summary: A cryptography library with minimal dependencies used for teaching cryptography
Author-email: Johan Galle <johan.galle@howest.be>
Project-URL: Homepage, https://github.com/Johangalle/Cryptography
Classifier: Programming Language :: Python :: 3
Classifier: License :: OSI Approved :: MIT License
Classifier: Operating System :: OS Independent
Requires-Python: >=3.7
License-File: LICENSE
